upm_oct_dataset_utils/__init__.py
upm_oct_dataset_utils/dataset_classes.py
upm_oct_dataset_utils/oct_processing_lib.py
upm_oct_dataset_utils/visualization_lib.py
upm_oct_dataset_utils/xml_processing_lib.py
upm_oct_dataset_utils-0.13.1.dist-info/LICENSE.txt
upm_oct_dataset_utils-0.13.1.dist-info/METADATA
upm_oct_dataset_utils-0.13.1.dist-info/WHEEL
upm_oct_dataset_utils-0.13.1.dist-info/top_level.txt
upm_oct_dataset_utils-0.13.1.dist-info/RECORD
