Metadata-Version: 2.1
Name: upm-oct-dataset-utils
Version: 0.13.1
Summary: Dataset utility package for UPM OCT/OCTA study (MS, NMO and RIS)
Home-page: https://github.com/pgmesa-upm/upm_oct_dataset_utils
Author: Pablo García Mesa
Author-email: pgmesa.sm@gmail.com
Classifier: Programming Language :: Python :: 3.9
Classifier: License :: OSI Approved :: GNU General Public License v3 or later (GPLv3+)
Classifier: Operating System :: OS Independent
Requires-Python: >=3.9
License-File: LICENSE.txt
Requires-Dist: matplotlib (>=3.5.2)
Requires-Dist: numpy (>=1.21.0)
Requires-Dist: opencv-python (>=4.5.5.64)
Requires-Dist: Pillow (>=9.1.1)
Requires-Dist: pandas (>=1.4.2)
Requires-Dist: pandas-read-xml (>=0.3.1)
Requires-Dist: tqdm (>=4.64.0)
